pysfa/SFA.py
pysfa/__init__.py
pysfa/constant.py
pysfa/dataset.py
pysfa/data/41Firm.csv
pysfa/data/electricityFirms.csv
pysfa/utils/__init__.py
pysfa/utils/tools.py
pysfa-0.8.dist-info/LICENSE
pysfa-0.8.dist-info/METADATA
pysfa-0.8.dist-info/WHEEL
pysfa-0.8.dist-info/top_level.txt
pysfa-0.8.dist-info/RECORD
