Metadata-Version: 2.1
Name: pysfa
Version: 0.8
Summary: A Python Package for Stochastic Frontier Analysis
Home-page: https://github.com/gEAPA/pySFA
Download-URL: https://pypi.org/project/pysfa/
Author: Sheng Dai, Zhiqiang Liao
Author-email: sheng.dai@utu.fi
License: MIT
Keywords: SFA,MLE,TE
Classifier: Development Status :: 5 - Production/Stable
Classifier: Intended Audience :: Science/Research
Classifier: Programming Language :: Python :: 3
Classifier: License :: OSI Approved :: MIT License
Classifier: Operating System :: OS Independent
License-File: LICENSE
Requires-Dist: numpy (>=1.19.2)
Requires-Dist: pandas (>=1.1.3)
Requires-Dist: scipy (>=1.5.2)
Requires-Dist: scikit-learn (>=1.2.2)
